ezaws/__init__.py
ezaws/exceptions.py
ezaws/cloudwatch/__init__.py
ezaws/cloudwatch/logs.py
ezaws/dynamodb/__init__.py
ezaws/dynamodb/dynamodb.py
ezaws/lambdas/__init__.py
ezaws/lambdas/lambdas.py
ezaws/models/__init__.py
ezaws/models/cloudwatch.py
ezaws/models/common.py
ezaws/models/dynamodb.py
ezaws/models/lambdas.py
ezaws/models/rds.py
ezaws/models/regions.py
ezaws/models/s3.py
ezaws/models/sqs.py
ezaws/models/ssm.py
ezaws/rds/__init__.py
ezaws/rds/rds.py
ezaws/s3/__init__.py
ezaws/s3/s3.py
ezaws/sqs/__init__.py
ezaws/sqs/functions.py
ezaws/sqs/messenger.py
ezaws/ssm/__init__.py
ezaws/ssm/parameter_store.py
ezaws/utils/__init__.py
ezaws/utils/timing.py
ezaws-0.31.dist-info/METADATA
ezaws-0.31.dist-info/WHEEL
ezaws-0.31.dist-info/top_level.txt
ezaws-0.31.dist-info/RECORD
