Metadata-Version: 2.1
Name: ezaws
Version: 0.31
Summary: An easy to use interface to AWS, ezaws.
Home-page: https://github.com/saidvandeklundert/ezaws
Project-URL: Bug Reports, https://github.com/saidvandeklundert/ezaws/issues
Project-URL: Source, https://github.com/saidvandeklundert/ezaws
Project-URL: Documentation, https://github.com/saidvandeklundert/ezaws
Classifier: Programming Language :: Python :: 3
Requires-Python: >=3.10, <4
